MANIFEST.in
README.rst
setup.py
docs/_build/html/.buildinfo
docs/_build/html/genindex.html
docs/_build/html/index.html
docs/_build/html/modules.html
docs/_build/html/objects.inv
docs/_build/html/py-modindex.html
docs/_build/html/s4api.html
docs/_build/html/s4api.models.html
docs/_build/html/s4sdk.html
docs/_build/html/s4sdk.models.html
docs/_build/html/search.html
docs/_build/html/searchindex.js
docs/_build/html/_sources/index.txt
docs/_build/html/_sources/modules.txt
docs/_build/html/_sources/s4api.models.txt
docs/_build/html/_sources/s4api.txt
docs/_build/html/_sources/s4sdk.models.txt
docs/_build/html/_sources/s4sdk.txt
docs/_build/html/_static/ajax-loader.gif
docs/_build/html/_static/alabaster.css
docs/_build/html/_static/basic.css
docs/_build/html/_static/comment-bright.png
docs/_build/html/_static/comment-close.png
docs/_build/html/_static/comment.png
docs/_build/html/_static/doctools.js
docs/_build/html/_static/down-pressed.png
docs/_build/html/_static/down.png
docs/_build/html/_static/file.png
docs/_build/html/_static/jquery-1.11.1.js
docs/_build/html/_static/jquery.js
docs/_build/html/_static/minus.png
docs/_build/html/_static/plus.png
docs/_build/html/_static/pygments.css
docs/_build/html/_static/searchtools.js
docs/_build/html/_static/underscore-1.3.1.js
docs/_build/html/_static/underscore.js
docs/_build/html/_static/up-pressed.png
docs/_build/html/_static/up.png
docs/_build/html/_static/websupport.js
s4api/__init__.py
s4api/fact_forge_api.py
s4api/graphdb_api.py
s4api/swagger.py
s4api/textanalytics_api.py
s4api.egg-info/PKG-INFO
s4api.egg-info/SOURCES.txt
s4api.egg-info/dependency_links.txt
s4api.egg-info/requires.txt
s4api.egg-info/top_level.txt
s4api/models/__init__.py
s4api/models/attachment.py
s4api/models/command_info.py
s4api/models/config.py
s4api/models/content_disposition.py
s4api/models/create.py
s4api/models/data_flavor.py
s4api/models/data_handler.py
s4api/models/data_source.py
s4api/models/media_type.py
s4api/models/service_request.py