Metadata-Version: 1.0
Name: s4api
Version: 0.1.2
Summary: Ontotext Self-Service Semantic Suite's SDK for Python3. For more information, visit http://s4.ontotext.com
Home-page: https://pypi.python.org/pypi/s4api
Author: Svetlin Slavov
Author-email: svetlin.slavov@ontotext.com
License: Apache License 2.0
Platform: UNKNOWN
